mypack/encode.py
mypack/npm.py
myPackageleeij-0.0.1.dist-info/LICENSE
myPackageleeij-0.0.1.dist-info/METADATA
myPackageleeij-0.0.1.dist-info/WHEEL
myPackageleeij-0.0.1.dist-info/top_level.txt
myPackageleeij-0.0.1.dist-info/RECORD
